{
    "capitulos": [
        {
            "id": 197254,
            "numero": 247,
            "titulo": "Capítulo 247",
            "dataPublicacao": "2026-02-03T00:26:30.937779+00:00"
        },
        {
            "id": 196861,
            "numero": 246,
            "titulo": "Capítulo 246",
            "dataPublicacao": "2026-02-01T21:32:05.786584+00:00"
        },
        {
            "id": 194679,
            "numero": 245,
            "titulo": "Capítulo 245",
            "dataPublicacao": "2026-01-27T02:47:00.991704+00:00"
        },
        {
            "id": 194677,
            "numero": 244,
            "titulo": "Capítulo 244",
            "dataPublicacao": "2026-01-27T02:45:42.684330+00:00"
        },
        {
            "id": 193472,
            "numero": 243,
            "titulo": "Capítulo 243",
            "dataPublicacao": "2026-01-20T00:45:41.323054+00:00"
        },
        {
            "id": 193471,
            "numero": 242,
            "titulo": "Capítulo 242",
            "dataPublicacao": "2026-01-20T00:44:51.928227+00:00"
        },
        {
            "id": 192740,
            "numero": 241,
            "titulo": "Capítulo 241",
            "dataPublicacao": "2026-01-15T22:56:28.816239+00:00"
        },
        {
            "id": 192739,
            "numero": 240,
            "titulo": "Capítulo 240",
            "dataPublicacao": "2026-01-15T22:56:18.929075+00:00"
        },
        {
            "id": 191063,
            "numero": 239,
            "titulo": "Capítulo 239",
            "dataPublicacao": "2026-01-07T18:51:43.044683+00:00"
        },
        {
            "id": 190190,
            "numero": 238,
            "titulo": "Capítulo 238",
            "dataPublicacao": "2026-01-04T19:38:32.672592+00:00"
        },
        {
            "id": 190260,
            "numero": 237,
            "titulo": "Capítulo 237",
            "dataPublicacao": "2026-01-04T23:37:48.999022+00:00"
        },
        {
            "id": 189201,
            "numero": 236,
            "titulo": "Capítulo 236",
            "dataPublicacao": "2025-12-28T00:10:27.790667+00:00"
        },
        {
            "id": 176611,
            "numero": 235,
            "titulo": "Capítulo 235",
            "dataPublicacao": "2025-12-22T12:25:42.507796+00:00"
        },
        {
            "id": 176257,
            "numero": 234,
            "titulo": "Capítulo 234",
            "dataPublicacao": "2025-12-21T10:59:37.334178+00:00"
        },
        {
            "id": 176256,
            "numero": 233,
            "titulo": "Capítulo 233",
            "dataPublicacao": "2025-12-21T10:58:45.530274+00:00"
        },
        {
            "id": 174494,
            "numero": 232,
            "titulo": "Capítulo 232",
            "dataPublicacao": "2025-12-15T02:36:52.975131+00:00"
        },
        {
            "id": 168045,
            "numero": 231,
            "titulo": "Capítulo 231",
            "dataPublicacao": "2025-11-30T09:29:28.420092+00:00"
        },
        {
            "id": 168044,
            "numero": 230,
            "titulo": "Capítulo 230",
            "dataPublicacao": "2025-11-30T09:29:15.484802+00:00"
        },
        {
            "id": 168043,
            "numero": 229,
            "titulo": "Capítulo 229",
            "dataPublicacao": "2025-11-30T09:29:03.566503+00:00"
        },
        {
            "id": 167104,
            "numero": 228,
            "titulo": "Capítulo 228",
            "dataPublicacao": "2025-11-25T01:34:26.996996+00:00"
        },
        {
            "id": 166520,
            "numero": 227,
            "titulo": "Capítulo 227",
            "dataPublicacao": "2025-11-21T17:54:50.703621+00:00"
        },
        {
            "id": 166519,
            "numero": 226,
            "titulo": "Capítulo 226",
            "dataPublicacao": "2025-11-21T17:54:05.099984+00:00"
        },
        {
            "id": 166518,
            "numero": 225,
            "titulo": "Capítulo 225",
            "dataPublicacao": "2025-11-21T17:53:20.068002+00:00"
        },
        {
            "id": 166517,
            "numero": 224,
            "titulo": "Capítulo 224",
            "dataPublicacao": "2025-11-21T17:52:30.698416+00:00"
        },
        {
            "id": 152734,
            "numero": 223,
            "titulo": "Capítulo 223",
            "dataPublicacao": "2025-10-29T01:16:02.118412+00:00"
        },
        {
            "id": 151565,
            "numero": 222,
            "titulo": "Capítulo 222",
            "dataPublicacao": "2025-10-23T04:38:17.387755+00:00"
        },
        {
            "id": 151043,
            "numero": 221,
            "titulo": "Capítulo 221",
            "dataPublicacao": "2025-10-21T07:01:25.623761+00:00"
        },
        {
            "id": 151042,
            "numero": 220,
            "titulo": "Capítulo 220",
            "dataPublicacao": "2025-10-21T07:01:24.534738+00:00"
        },
        {
            "id": 144292,
            "numero": 219,
            "titulo": "Capítulo 219",
            "dataPublicacao": "2025-10-14T15:57:33.686906+00:00"
        },
        {
            "id": 144291,
            "numero": 218,
            "titulo": "Capítulo 218",
            "dataPublicacao": "2025-10-14T15:57:32.862229+00:00"
        },
        {
            "id": 143699,
            "numero": 217,
            "titulo": "Capítulo 217",
            "dataPublicacao": "2025-10-12T19:19:53.104039+00:00"
        },
        {
            "id": 143698,
            "numero": 216,
            "titulo": "Capítulo 216",
            "dataPublicacao": "2025-10-12T19:19:53.104904+00:00"
        },
        {
            "id": 143697,
            "numero": 215,
            "titulo": "Capítulo 215",
            "dataPublicacao": "2025-10-12T19:19:49.533839+00:00"
        },
        {
            "id": 143696,
            "numero": 214,
            "titulo": "Capítulo 214",
            "dataPublicacao": "2025-10-12T19:20:10.742130+00:00"
        },
        {
            "id": 143695,
            "numero": 213,
            "titulo": "Capítulo 213",
            "dataPublicacao": "2025-10-12T19:19:44.462143+00:00"
        },
        {
            "id": 143694,
            "numero": 212,
            "titulo": "Capítulo 212",
            "dataPublicacao": "2025-10-12T19:19:39.757416+00:00"
        },
        {
            "id": 143693,
            "numero": 211,
            "titulo": "Capítulo 211",
            "dataPublicacao": "2025-10-12T19:19:45.717253+00:00"
        },
        {
            "id": 143692,
            "numero": 210,
            "titulo": "Capítulo 210",
            "dataPublicacao": "2025-10-12T19:19:36.248464+00:00"
        },
        {
            "id": 77080,
            "numero": 209,
            "titulo": "Capítulo 209",
            "dataPublicacao": "2025-09-04T01:18:34.244881+00:00"
        },
        {
            "id": 76855,
            "numero": 208,
            "titulo": "Capítulo 208",
            "dataPublicacao": "2025-09-02T23:13:05.115682+00:00"
        },
        {
            "id": 76611,
            "numero": 207,
            "titulo": "Capítulo 207",
            "dataPublicacao": "2025-08-24T12:53:20.255697+00:00"
        },
        {
            "id": 64053,
            "numero": 206,
            "titulo": "Capítulo 206",
            "dataPublicacao": "2025-08-21T15:17:35.035493+00:00"
        },
        {
            "id": 64052,
            "numero": 205,
            "titulo": "Capítulo 205",
            "dataPublicacao": "2025-08-21T15:17:33.942065+00:00"
        },
        {
            "id": 52455,
            "numero": 204,
            "titulo": "Capítulo 204",
            "dataPublicacao": "2025-08-16T23:00:05.920390+00:00"
        },
        {
            "id": 52454,
            "numero": 203,
            "titulo": "Capítulo 203",
            "dataPublicacao": "2025-08-16T23:00:05.359202+00:00"
        },
        {
            "id": 49696,
            "numero": 202,
            "titulo": "Capítulo 202",
            "dataPublicacao": "2025-08-16T01:44:25.500123+00:00"
        },
        {
            "id": 49699,
            "numero": 201,
            "titulo": "Capítulo 201",
            "dataPublicacao": "2025-08-16T01:44:24.171553+00:00"
        },
        {
            "id": 49698,
            "numero": 200,
            "titulo": "Capítulo 200",
            "dataPublicacao": "2025-08-16T01:44:26.107046+00:00"
        },
        {
            "id": 49695,
            "numero": 199,
            "titulo": "Capítulo 199",
            "dataPublicacao": "2025-08-16T01:44:23.858586+00:00"
        },
        {
            "id": 49697,
            "numero": 198,
            "titulo": "Capítulo 198",
            "dataPublicacao": "2025-08-16T01:44:24.479736+00:00"
        },
        {
            "id": 2613,
            "numero": 197,
            "titulo": "Capítulo 197",
            "dataPublicacao": "2025-08-01T09:11:15.856861+00:00"
        },
        {
            "id": 2612,
            "numero": 196,
            "titulo": "Capítulo 196",
            "dataPublicacao": "2025-08-01T09:12:02.718093+00:00"
        },
        {
            "id": 2611,
            "numero": 195,
            "titulo": "Capítulo 195",
            "dataPublicacao": "2025-08-01T09:11:15.232202+00:00"
        },
        {
            "id": 2610,
            "numero": 194,
            "titulo": "Capítulo 194",
            "dataPublicacao": "2025-08-01T09:11:07.676307+00:00"
        },
        {
            "id": 2609,
            "numero": 193,
            "titulo": "Capítulo 193",
            "dataPublicacao": "2025-08-01T09:10:47.878629+00:00"
        },
        {
            "id": 2608,
            "numero": 192,
            "titulo": "Capítulo 192",
            "dataPublicacao": "2025-08-01T09:10:55.997045+00:00"
        },
        {
            "id": 2607,
            "numero": 191,
            "titulo": "Capítulo 191",
            "dataPublicacao": "2025-08-01T09:10:50.455489+00:00"
        },
        {
            "id": 2606,
            "numero": 190,
            "titulo": "Capítulo 190",
            "dataPublicacao": "2025-08-01T09:11:06.142933+00:00"
        },
        {
            "id": 2605,
            "numero": 189,
            "titulo": "Capítulo 189",
            "dataPublicacao": "2025-08-01T09:11:04.931442+00:00"
        },
        {
            "id": 2604,
            "numero": 188,
            "titulo": "Capítulo 188",
            "dataPublicacao": "2025-08-01T09:11:06.993592+00:00"
        },
        {
            "id": 168118,
            "numero": 187,
            "titulo": "Capítulo 187",
            "dataPublicacao": "2025-11-30T19:58:07.474535+00:00"
        },
        {
            "id": 168116,
            "numero": 186,
            "titulo": "Capítulo 186",
            "dataPublicacao": "2025-11-30T19:57:59.560014+00:00"
        },
        {
            "id": 168115,
            "numero": 185,
            "titulo": "Capítulo 185",
            "dataPublicacao": "2025-11-30T19:57:50.715633+00:00"
        },
        {
            "id": 2600,
            "numero": 184,
            "titulo": "Capítulo 184",
            "dataPublicacao": "2025-08-01T09:10:32.066795+00:00"
        },
        {
            "id": 2599,
            "numero": 183,
            "titulo": "Capítulo 183",
            "dataPublicacao": "2025-08-01T09:10:28.135858+00:00"
        },
        {
            "id": 2598,
            "numero": 182,
            "titulo": "Capítulo 182",
            "dataPublicacao": "2025-08-01T09:10:26.830853+00:00"
        },
        {
            "id": 2597,
            "numero": 181,
            "titulo": "Capítulo 181",
            "dataPublicacao": "2025-08-01T09:10:30.910966+00:00"
        },
        {
            "id": 2596,
            "numero": 180,
            "titulo": "Capítulo 180",
            "dataPublicacao": "2025-08-01T09:10:23.043414+00:00"
        },
        {
            "id": 2595,
            "numero": 179,
            "titulo": "Capítulo 179",
            "dataPublicacao": "2025-08-01T09:10:22.087553+00:00"
        },
        {
            "id": 2594,
            "numero": 178,
            "titulo": "Capítulo 178",
            "dataPublicacao": "2025-08-01T09:10:27.538203+00:00"
        },
        {
            "id": 2593,
            "numero": 177,
            "titulo": "Capítulo 177",
            "dataPublicacao": "2025-08-01T09:10:51.459028+00:00"
        },
        {
            "id": 2592,
            "numero": 176,
            "titulo": "Capítulo 176",
            "dataPublicacao": "2025-08-01T09:10:34.747746+00:00"
        },
        {
            "id": 2591,
            "numero": 175,
            "titulo": "Capítulo 175",
            "dataPublicacao": "2025-08-01T09:10:28.709119+00:00"
        },
        {
            "id": 2590,
            "numero": 174,
            "titulo": "Capítulo 174",
            "dataPublicacao": "2025-08-01T09:10:18.673107+00:00"
        },
        {
            "id": 2589,
            "numero": 173,
            "titulo": "Capítulo 173",
            "dataPublicacao": "2025-08-01T09:10:17.226763+00:00"
        },
        {
            "id": 2588,
            "numero": 172,
            "titulo": "Capítulo 172",
            "dataPublicacao": "2025-08-01T09:10:19.673641+00:00"
        },
        {
            "id": 2587,
            "numero": 171,
            "titulo": "Capítulo 171",
            "dataPublicacao": "2025-08-01T09:10:15.193449+00:00"
        },
        {
            "id": 2586,
            "numero": 170,
            "titulo": "Capítulo 170",
            "dataPublicacao": "2025-08-01T09:10:14.712093+00:00"
        },
        {
            "id": 2585,
            "numero": 169,
            "titulo": "Capítulo 169",
            "dataPublicacao": "2025-08-01T09:10:08.500052+00:00"
        },
        {
            "id": 2584,
            "numero": 168,
            "titulo": "Capítulo 168",
            "dataPublicacao": "2025-08-01T09:10:12.828839+00:00"
        },
        {
            "id": 2583,
            "numero": 167,
            "titulo": "Capítulo 167",
            "dataPublicacao": "2025-08-01T09:10:10.780235+00:00"
        },
        {
            "id": 2582,
            "numero": 166,
            "titulo": "Capítulo 166",
            "dataPublicacao": "2025-08-01T09:10:13.354578+00:00"
        },
        {
            "id": 2581,
            "numero": 165,
            "titulo": "Capítulo 165",
            "dataPublicacao": "2025-08-01T09:10:09.015669+00:00"
        },
        {
            "id": 2580,
            "numero": 164,
            "titulo": "Capítulo 164",
            "dataPublicacao": "2025-08-01T09:10:11.712334+00:00"
        },
        {
            "id": 2579,
            "numero": 163,
            "titulo": "Capítulo 163",
            "dataPublicacao": "2025-08-01T09:10:02.667938+00:00"
        },
        {
            "id": 2578,
            "numero": 162,
            "titulo": "Capítulo 162",
            "dataPublicacao": "2025-08-01T09:10:01.267732+00:00"
        },
        {
            "id": 2577,
            "numero": 161,
            "titulo": "Capítulo 161",
            "dataPublicacao": "2025-08-01T09:10:07.823927+00:00"
        },
        {
            "id": 2576,
            "numero": 160,
            "titulo": "Capítulo 160",
            "dataPublicacao": "2025-08-01T09:09:57.528390+00:00"
        },
        {
            "id": 2575,
            "numero": 159,
            "titulo": "Capítulo 159",
            "dataPublicacao": "2025-08-01T09:09:59.782576+00:00"
        },
        {
            "id": 2574,
            "numero": 158,
            "titulo": "Capítulo 158",
            "dataPublicacao": "2025-08-01T09:10:16.634781+00:00"
        },
        {
            "id": 2573,
            "numero": 157,
            "titulo": "Capítulo 157",
            "dataPublicacao": "2025-08-01T09:09:53.430717+00:00"
        },
        {
            "id": 2572,
            "numero": 156,
            "titulo": "Capítulo 156",
            "dataPublicacao": "2025-08-01T09:09:58.077850+00:00"
        },
        {
            "id": 2571,
            "numero": 155,
            "titulo": "Capítulo 155",
            "dataPublicacao": "2025-08-01T09:09:52.881495+00:00"
        },
        {
            "id": 2570,
            "numero": 154,
            "titulo": "Capítulo 154",
            "dataPublicacao": "2025-08-01T09:09:50.074808+00:00"
        },
        {
            "id": 2569,
            "numero": 153,
            "titulo": "Capítulo 153",
            "dataPublicacao": "2025-08-01T09:09:56.085388+00:00"
        },
        {
            "id": 2568,
            "numero": 152,
            "titulo": "Capítulo 152",
            "dataPublicacao": "2025-08-01T09:09:48.776419+00:00"
        },
        {
            "id": 2567,
            "numero": 151,
            "titulo": "Capítulo 151",
            "dataPublicacao": "2025-08-01T09:09:46.517429+00:00"
        },
        {
            "id": 2566,
            "numero": 150,
            "titulo": "Capítulo 150",
            "dataPublicacao": "2025-08-01T09:09:48.195501+00:00"
        },
        {
            "id": 2565,
            "numero": 149,
            "titulo": "Capítulo 149",
            "dataPublicacao": "2025-08-01T09:09:51.028712+00:00"
        },
        {
            "id": 2564,
            "numero": 148,
            "titulo": "Capítulo 148",
            "dataPublicacao": "2025-08-01T09:09:57.012131+00:00"
        },
        {
            "id": 2563,
            "numero": 147,
            "titulo": "Capítulo 147",
            "dataPublicacao": "2025-08-01T09:09:42.074174+00:00"
        },
        {
            "id": 2562,
            "numero": 146,
            "titulo": "Capítulo 146",
            "dataPublicacao": "2025-08-01T09:09:42.628515+00:00"
        },
        {
            "id": 2561,
            "numero": 145,
            "titulo": "Capítulo 145",
            "dataPublicacao": "2025-08-01T09:09:39.126576+00:00"
        },
        {
            "id": 2560,
            "numero": 144,
            "titulo": "Capítulo 144",
            "dataPublicacao": "2025-08-01T09:09:37.678637+00:00"
        },
        {
            "id": 2559,
            "numero": 143,
            "titulo": "Capítulo 143",
            "dataPublicacao": "2025-08-01T09:09:40.098922+00:00"
        },
        {
            "id": 2558,
            "numero": 142,
            "titulo": "Capítulo 142",
            "dataPublicacao": "2025-08-01T09:09:37.111156+00:00"
        },
        {
            "id": 2557,
            "numero": 141,
            "titulo": "Capítulo 141",
            "dataPublicacao": "2025-08-01T09:09:43.983433+00:00"
        },
        {
            "id": 2556,
            "numero": 140,
            "titulo": "Capítulo 140",
            "dataPublicacao": "2025-08-01T09:09:41.170340+00:00"
        },
        {
            "id": 2555,
            "numero": 139,
            "titulo": "Capítulo 139",
            "dataPublicacao": "2025-08-01T09:09:32.258997+00:00"
        },
        {
            "id": 2554,
            "numero": 138,
            "titulo": "Capítulo 138",
            "dataPublicacao": "2025-08-01T09:09:34.345422+00:00"
        },
        {
            "id": 2553,
            "numero": 137,
            "titulo": "Capítulo 137",
            "dataPublicacao": "2025-08-01T09:09:25.583941+00:00"
        },
        {
            "id": 2552,
            "numero": 136,
            "titulo": "Capítulo 136",
            "dataPublicacao": "2025-08-01T09:09:24.670687+00:00"
        },
        {
            "id": 2551,
            "numero": 135,
            "titulo": "Capítulo 135",
            "dataPublicacao": "2025-08-01T09:09:26.654510+00:00"
        },
        {
            "id": 2550,
            "numero": 134,
            "titulo": "Capítulo 134",
            "dataPublicacao": "2025-08-01T09:09:27.217834+00:00"
        },
        {
            "id": 2549,
            "numero": 133,
            "titulo": "Capítulo 133",
            "dataPublicacao": "2025-08-01T09:09:15.707447+00:00"
        },
        {
            "id": 2548,
            "numero": 132,
            "titulo": "Capítulo 132",
            "dataPublicacao": "2025-08-01T09:09:17.830417+00:00"
        },
        {
            "id": 2547,
            "numero": 131,
            "titulo": "Capítulo 131",
            "dataPublicacao": "2025-08-01T09:09:16.283856+00:00"
        },
        {
            "id": 2546,
            "numero": 130,
            "titulo": "Capítulo 130",
            "dataPublicacao": "2025-08-01T09:09:10.963802+00:00"
        },
        {
            "id": 191947,
            "numero": 129,
            "titulo": "Capítulo 129",
            "dataPublicacao": "2026-01-09T15:55:39.091405+00:00"
        },
        {
            "id": 2544,
            "numero": 128,
            "titulo": "Capítulo 128",
            "dataPublicacao": "2025-08-01T09:09:04.274595+00:00"
        },
        {
            "id": 2543,
            "numero": 127,
            "titulo": "Capítulo 127",
            "dataPublicacao": "2025-08-01T09:09:19.756444+00:00"
        },
        {
            "id": 2542,
            "numero": 126,
            "titulo": "Capítulo 126",
            "dataPublicacao": "2025-08-01T09:09:13.838688+00:00"
        },
        {
            "id": 2541,
            "numero": 125,
            "titulo": "Capítulo 125",
            "dataPublicacao": "2025-08-01T09:09:13.175162+00:00"
        },
        {
            "id": 2540,
            "numero": 124,
            "titulo": "Capítulo 124",
            "dataPublicacao": "2025-08-01T09:09:32.970207+00:00"
        },
        {
            "id": 2539,
            "numero": 123,
            "titulo": "Capítulo 123",
            "dataPublicacao": "2025-08-01T09:09:35.270830+00:00"
        },
        {
            "id": 2538,
            "numero": 122,
            "titulo": "Capítulo 122",
            "dataPublicacao": "2025-08-01T09:08:54.190805+00:00"
        },
        {
            "id": 2537,
            "numero": 121,
            "titulo": "Capítulo 121",
            "dataPublicacao": "2025-08-01T09:09:00.408750+00:00"
        },
        {
            "id": 2536,
            "numero": 120,
            "titulo": "Capítulo 120",
            "dataPublicacao": "2025-08-01T09:08:58.133043+00:00"
        },
        {
            "id": 2535,
            "numero": 119,
            "titulo": "Capítulo 119",
            "dataPublicacao": "2025-08-01T09:08:52.274210+00:00"
        },
        {
            "id": 2534,
            "numero": 118,
            "titulo": "Capítulo 118",
            "dataPublicacao": "2025-08-01T09:08:57.186558+00:00"
        },
        {
            "id": 2533,
            "numero": 117,
            "titulo": "Capítulo 117",
            "dataPublicacao": "2025-08-01T09:08:55.859493+00:00"
        },
        {
            "id": 2532,
            "numero": 116,
            "titulo": "Capítulo 116",
            "dataPublicacao": "2025-08-01T09:08:49.150630+00:00"
        },
        {
            "id": 2531,
            "numero": 115,
            "titulo": "Capítulo 115",
            "dataPublicacao": "2025-08-01T09:08:50.156688+00:00"
        },
        {
            "id": 2530,
            "numero": 114,
            "titulo": "Capítulo 114",
            "dataPublicacao": "2025-08-01T09:08:39.247211+00:00"
        },
        {
            "id": 2529,
            "numero": 113,
            "titulo": "Capítulo 113",
            "dataPublicacao": "2025-08-01T09:08:52.885317+00:00"
        },
        {
            "id": 2528,
            "numero": 112,
            "titulo": "Capítulo 112",
            "dataPublicacao": "2025-08-01T09:08:38.740185+00:00"
        },
        {
            "id": 2527,
            "numero": 111,
            "titulo": "Capítulo 111",
            "dataPublicacao": "2025-08-01T09:08:32.893720+00:00"
        },
        {
            "id": 2526,
            "numero": 110,
            "titulo": "Capítulo 110",
            "dataPublicacao": "2025-08-01T09:08:34.346745+00:00"
        },
        {
            "id": 2525,
            "numero": 109,
            "titulo": "Capítulo 109",
            "dataPublicacao": "2025-08-01T09:08:34.903767+00:00"
        },
        {
            "id": 2524,
            "numero": 108,
            "titulo": "Capítulo 108",
            "dataPublicacao": "2025-08-01T09:08:37.218158+00:00"
        },
        {
            "id": 2523,
            "numero": 107,
            "titulo": "Capítulo 107",
            "dataPublicacao": "2025-08-01T09:08:36.688320+00:00"
        },
        {
            "id": 2522,
            "numero": 106,
            "titulo": "Capítulo 106",
            "dataPublicacao": "2025-08-01T09:08:22.718993+00:00"
        },
        {
            "id": 2521,
            "numero": 105,
            "titulo": "Capítulo 105",
            "dataPublicacao": "2025-08-01T09:08:55.322835+00:00"
        },
        {
            "id": 2520,
            "numero": 104,
            "titulo": "Capítulo 104",
            "dataPublicacao": "2025-08-01T09:08:20.329102+00:00"
        },
        {
            "id": 2519,
            "numero": 103,
            "titulo": "Capítulo 103",
            "dataPublicacao": "2025-08-01T09:08:30.351416+00:00"
        },
        {
            "id": 2518,
            "numero": 102,
            "titulo": "Capítulo 102",
            "dataPublicacao": "2025-08-01T09:08:19.241573+00:00"
        },
        {
            "id": 2517,
            "numero": 101,
            "titulo": "Capítulo 101",
            "dataPublicacao": "2025-08-01T09:08:12.039119+00:00"
        },
        {
            "id": 2516,
            "numero": 100,
            "titulo": "Capítulo 100",
            "dataPublicacao": "2025-08-01T09:08:21.220848+00:00"
        },
        {
            "id": 2515,
            "numero": 99,
            "titulo": "Capítulo 99",
            "dataPublicacao": "2025-08-01T09:08:12.948612+00:00"
        },
        {
            "id": 2514,
            "numero": 98,
            "titulo": "Capítulo 98",
            "dataPublicacao": "2025-08-01T09:08:09.787295+00:00"
        },
        {
            "id": 2513,
            "numero": 97,
            "titulo": "Capítulo 97",
            "dataPublicacao": "2025-08-01T09:08:09.216901+00:00"
        },
        {
            "id": 2512,
            "numero": 96,
            "titulo": "Capítulo 96",
            "dataPublicacao": "2025-08-01T09:08:14.335678+00:00"
        },
        {
            "id": 2511,
            "numero": 95,
            "titulo": "Capítulo 95",
            "dataPublicacao": "2025-08-01T09:08:04.427856+00:00"
        },
        {
            "id": 2510,
            "numero": 94,
            "titulo": "Capítulo 94",
            "dataPublicacao": "2025-08-01T09:08:17.053982+00:00"
        },
        {
            "id": 2509,
            "numero": 93,
            "titulo": "Capítulo 93",
            "dataPublicacao": "2025-08-01T09:08:05.136059+00:00"
        },
        {
            "id": 2508,
            "numero": 92,
            "titulo": "Capítulo 92",
            "dataPublicacao": "2025-08-01T09:07:57.474991+00:00"
        },
        {
            "id": 2507,
            "numero": 91,
            "titulo": "Capítulo 91",
            "dataPublicacao": "2025-08-01T09:07:51.585233+00:00"
        },
        {
            "id": 2506,
            "numero": 90,
            "titulo": "Capítulo 90",
            "dataPublicacao": "2025-08-01T09:07:49.657428+00:00"
        },
        {
            "id": 2505,
            "numero": 89,
            "titulo": "Capítulo 89",
            "dataPublicacao": "2025-08-01T09:07:55.661216+00:00"
        },
        {
            "id": 2504,
            "numero": 88,
            "titulo": "Capítulo 88",
            "dataPublicacao": "2025-08-01T09:08:00.816837+00:00"
        },
        {
            "id": 2503,
            "numero": 87,
            "titulo": "Capítulo 87",
            "dataPublicacao": "2025-08-01T09:07:43.591565+00:00"
        },
        {
            "id": 2502,
            "numero": 86,
            "titulo": "Capítulo 86",
            "dataPublicacao": "2025-08-01T09:07:51.064239+00:00"
        },
        {
            "id": 2501,
            "numero": 85,
            "titulo": "Capítulo 85",
            "dataPublicacao": "2025-08-01T09:07:40.319984+00:00"
        },
        {
            "id": 2500,
            "numero": 84,
            "titulo": "Capítulo 84",
            "dataPublicacao": "2025-08-01T09:07:35.867262+00:00"
        },
        {
            "id": 2499,
            "numero": 83,
            "titulo": "Capítulo 83",
            "dataPublicacao": "2025-08-01T09:07:33.224500+00:00"
        },
        {
            "id": 2498,
            "numero": 82,
            "titulo": "Capítulo 82",
            "dataPublicacao": "2025-08-01T09:07:27.444459+00:00"
        },
        {
            "id": 2497,
            "numero": 81,
            "titulo": "Capítulo 81",
            "dataPublicacao": "2025-08-01T09:07:25.524259+00:00"
        },
        {
            "id": 2496,
            "numero": 80,
            "titulo": "Capítulo 80",
            "dataPublicacao": "2025-08-01T09:07:18.583861+00:00"
        },
        {
            "id": 2495,
            "numero": 79,
            "titulo": "Capítulo 79",
            "dataPublicacao": "2025-08-01T09:07:48.701523+00:00"
        },
        {
            "id": 2494,
            "numero": 78,
            "titulo": "Capítulo 78",
            "dataPublicacao": "2025-08-01T09:07:52.994149+00:00"
        },
        {
            "id": 2493,
            "numero": 77,
            "titulo": "Capítulo 77",
            "dataPublicacao": "2025-08-01T09:07:53.576634+00:00"
        },
        {
            "id": 2492,
            "numero": 76,
            "titulo": "Capítulo 76",
            "dataPublicacao": "2025-08-01T09:07:37.515788+00:00"
        },
        {
            "id": 2491,
            "numero": 75,
            "titulo": "Capítulo 75",
            "dataPublicacao": "2025-08-01T09:07:59.732345+00:00"
        },
        {
            "id": 2490,
            "numero": 74,
            "titulo": "Capítulo 74",
            "dataPublicacao": "2025-08-01T09:07:56.905126+00:00"
        },
        {
            "id": 2489,
            "numero": 73,
            "titulo": "Capítulo 73",
            "dataPublicacao": "2025-08-01T09:07:32.126060+00:00"
        },
        {
            "id": 2488,
            "numero": 72,
            "titulo": "Capítulo 72",
            "dataPublicacao": "2025-08-01T09:07:36.908600+00:00"
        },
        {
            "id": 2487,
            "numero": 71,
            "titulo": "Capítulo 71",
            "dataPublicacao": "2025-08-01T09:07:17.553869+00:00"
        },
        {
            "id": 2486,
            "numero": 70,
            "titulo": "Capítulo 70",
            "dataPublicacao": "2025-08-01T09:07:04.894181+00:00"
        },
        {
            "id": 2485,
            "numero": 69,
            "titulo": "Capítulo 69",
            "dataPublicacao": "2025-08-01T09:06:59.207084+00:00"
        },
        {
            "id": 2484,
            "numero": 68,
            "titulo": "Capítulo 68",
            "dataPublicacao": "2025-08-01T09:07:10.453455+00:00"
        },
        {
            "id": 2483,
            "numero": 67,
            "titulo": "Capítulo 67",
            "dataPublicacao": "2025-08-01T09:06:56.350933+00:00"
        },
        {
            "id": 2482,
            "numero": 66,
            "titulo": "Capítulo 66",
            "dataPublicacao": "2025-08-01T09:06:51.341210+00:00"
        },
        {
            "id": 2481,
            "numero": 65,
            "titulo": "Capítulo 65",
            "dataPublicacao": "2025-08-01T09:06:50.365838+00:00"
        },
        {
            "id": 2480,
            "numero": 64,
            "titulo": "Capítulo 64",
            "dataPublicacao": "2025-08-01T09:06:47.944134+00:00"
        },
        {
            "id": 2479,
            "numero": 63,
            "titulo": "Capítulo 63",
            "dataPublicacao": "2025-08-01T09:06:59.731860+00:00"
        },
        {
            "id": 2478,
            "numero": 62,
            "titulo": "Capítulo 62",
            "dataPublicacao": "2025-08-01T09:07:09.081388+00:00"
        },
        {
            "id": 2477,
            "numero": 61,
            "titulo": "Capítulo 61",
            "dataPublicacao": "2025-08-01T09:06:41.796434+00:00"
        },
        {
            "id": 2476,
            "numero": 60,
            "titulo": "Capítulo 60",
            "dataPublicacao": "2025-08-01T09:06:40.936792+00:00"
        },
        {
            "id": 2475,
            "numero": 59,
            "titulo": "Capítulo 59",
            "dataPublicacao": "2025-08-01T09:06:37.498217+00:00"
        },
        {
            "id": 2474,
            "numero": 58,
            "titulo": "Capítulo 58",
            "dataPublicacao": "2025-08-01T09:06:39.329218+00:00"
        },
        {
            "id": 2473,
            "numero": 57,
            "titulo": "Capítulo 57",
            "dataPublicacao": "2025-08-01T09:06:31.831342+00:00"
        },
        {
            "id": 2472,
            "numero": 56,
            "titulo": "Capítulo 56",
            "dataPublicacao": "2025-08-01T09:06:29.546644+00:00"
        },
        {
            "id": 2471,
            "numero": 55,
            "titulo": "Capítulo 55",
            "dataPublicacao": "2025-08-01T09:06:30.894951+00:00"
        },
        {
            "id": 2470,
            "numero": 54,
            "titulo": "Capítulo 54",
            "dataPublicacao": "2025-08-01T09:06:29.000675+00:00"
        },
        {
            "id": 2469,
            "numero": 53,
            "titulo": "Capítulo 53",
            "dataPublicacao": "2025-08-01T09:06:25.756303+00:00"
        },
        {
            "id": 2468,
            "numero": 52,
            "titulo": "Capítulo 52",
            "dataPublicacao": "2025-08-01T09:06:38.738994+00:00"
        },
        {
            "id": 2467,
            "numero": 51,
            "titulo": "Capítulo 51",
            "dataPublicacao": "2025-08-01T09:06:21.187865+00:00"
        },
        {
            "id": 2466,
            "numero": 50,
            "titulo": "Capítulo 50",
            "dataPublicacao": "2025-08-01T09:06:17.289296+00:00"
        },
        {
            "id": 2465,
            "numero": 49,
            "titulo": "Capítulo 49",
            "dataPublicacao": "2025-08-01T09:06:16.269945+00:00"
        },
        {
            "id": 2464,
            "numero": 48,
            "titulo": "Capítulo 48",
            "dataPublicacao": "2025-08-01T09:06:03.848498+00:00"
        },
        {
            "id": 2463,
            "numero": 47,
            "titulo": "Capítulo 47",
            "dataPublicacao": "2025-08-01T09:06:12.464424+00:00"
        },
        {
            "id": 2462,
            "numero": 46,
            "titulo": "Capítulo 46",
            "dataPublicacao": "2025-08-01T09:06:21.685396+00:00"
        },
        {
            "id": 77066,
            "numero": 45.5,
            "titulo": "Capítulo 45.5",
            "dataPublicacao": "2025-09-03T19:36:19.891780+00:00"
        },
        {
            "id": 2461,
            "numero": 45,
            "titulo": "Capítulo 45",
            "dataPublicacao": "2025-08-01T09:05:53.627289+00:00"
        },
        {
            "id": 2460,
            "numero": 44,
            "titulo": "Capítulo 44",
            "dataPublicacao": "2025-08-01T09:05:49.563158+00:00"
        },
        {
            "id": 2459,
            "numero": 43,
            "titulo": "Capítulo 43",
            "dataPublicacao": "2025-08-01T09:05:53.107554+00:00"
        },
        {
            "id": 2458,
            "numero": 42,
            "titulo": "Capítulo 42",
            "dataPublicacao": "2025-08-01T09:06:24.460249+00:00"
        },
        {
            "id": 2457,
            "numero": 41,
            "titulo": "Capítulo 41",
            "dataPublicacao": "2025-08-01T09:05:44.514255+00:00"
        },
        {
            "id": 169380,
            "numero": 40,
            "titulo": "Capítulo 40",
            "dataPublicacao": "2025-12-04T00:27:03.293457+00:00"
        },
        {
            "id": 169415,
            "numero": 39,
            "titulo": "Capítulo 39",
            "dataPublicacao": "2025-12-04T01:46:56.988108+00:00"
        },
        {
            "id": 169379,
            "numero": 38,
            "titulo": "Capítulo 38",
            "dataPublicacao": "2025-12-04T00:26:55.476390+00:00"
        },
        {
            "id": 2453,
            "numero": 37,
            "titulo": "Capítulo 37",
            "dataPublicacao": "2025-08-01T09:05:26.805966+00:00"
        },
        {
            "id": 2452,
            "numero": 36,
            "titulo": "Capítulo 36",
            "dataPublicacao": "2025-08-01T09:05:25.020683+00:00"
        },
        {
            "id": 77068,
            "numero": 35.5,
            "titulo": "Capítulo 35.5",
            "dataPublicacao": "2025-10-12T19:19:58.216017+00:00"
        },
        {
            "id": 2451,
            "numero": 35,
            "titulo": "Capítulo 35",
            "dataPublicacao": "2025-08-01T09:06:00.325196+00:00"
        },
        {
            "id": 2450,
            "numero": 34,
            "titulo": "Capítulo 34",
            "dataPublicacao": "2025-08-01T09:05:12.148561+00:00"
        },
        {
            "id": 2449,
            "numero": 33,
            "titulo": "Capítulo 33",
            "dataPublicacao": "2025-08-01T09:05:10.711825+00:00"
        },
        {
            "id": 2448,
            "numero": 32,
            "titulo": "Capítulo 32",
            "dataPublicacao": "2025-08-01T09:05:08.051082+00:00"
        },
        {
            "id": 2447,
            "numero": 31,
            "titulo": "Capítulo 31",
            "dataPublicacao": "2025-08-01T09:05:08.763066+00:00"
        },
        {
            "id": 2446,
            "numero": 30,
            "titulo": "Capítulo 30",
            "dataPublicacao": "2025-08-01T09:05:17.466494+00:00"
        },
        {
            "id": 2445,
            "numero": 29,
            "titulo": "Capítulo 29",
            "dataPublicacao": "2025-08-01T09:05:00.431441+00:00"
        },
        {
            "id": 2444,
            "numero": 28,
            "titulo": "Capítulo 28",
            "dataPublicacao": "2025-08-01T09:04:59.528644+00:00"
        },
        {
            "id": 2443,
            "numero": 27,
            "titulo": "Capítulo 27",
            "dataPublicacao": "2025-08-01T09:04:58.359604+00:00"
        },
        {
            "id": 77067,
            "numero": 26.5,
            "titulo": "Capítulo 26.5",
            "dataPublicacao": "2025-09-03T19:59:26.489824+00:00"
        },
        {
            "id": 2442,
            "numero": 26,
            "titulo": "Capítulo 26",
            "dataPublicacao": "2025-08-01T09:04:57.477364+00:00"
        },
        {
            "id": 2441,
            "numero": 25,
            "titulo": "Capítulo 25",
            "dataPublicacao": "2025-08-01T09:04:52.890422+00:00"
        },
        {
            "id": 2440,
            "numero": 24,
            "titulo": "Capítulo 24",
            "dataPublicacao": "2025-08-01T09:04:49.690863+00:00"
        },
        {
            "id": 2439,
            "numero": 23,
            "titulo": "Capítulo 23",
            "dataPublicacao": "2025-08-01T09:04:45.902502+00:00"
        },
        {
            "id": 2438,
            "numero": 22,
            "titulo": "Capítulo 22",
            "dataPublicacao": "2025-08-01T09:04:42.348638+00:00"
        },
        {
            "id": 2437,
            "numero": 21,
            "titulo": "Capítulo 21",
            "dataPublicacao": "2025-08-01T09:04:40.344717+00:00"
        },
        {
            "id": 2436,
            "numero": 20,
            "titulo": "Capítulo 20",
            "dataPublicacao": "2025-08-01T09:04:35.247095+00:00"
        },
        {
            "id": 2435,
            "numero": 19,
            "titulo": "Capítulo 19",
            "dataPublicacao": "2025-08-01T09:04:50.199672+00:00"
        },
        {
            "id": 2434,
            "numero": 18,
            "titulo": "Capítulo 18",
            "dataPublicacao": "2025-08-01T09:04:32.166841+00:00"
        },
        {
            "id": 2433,
            "numero": 17,
            "titulo": "Capítulo 17",
            "dataPublicacao": "2025-08-01T09:04:39.823809+00:00"
        },
        {
            "id": 2432,
            "numero": 16,
            "titulo": "Capítulo 16",
            "dataPublicacao": "2025-08-01T09:04:26.192197+00:00"
        },
        {
            "id": 2431,
            "numero": 15,
            "titulo": "Capítulo 15",
            "dataPublicacao": "2025-08-01T09:04:43.316666+00:00"
        },
        {
            "id": 2430,
            "numero": 14,
            "titulo": "Capítulo 14",
            "dataPublicacao": "2025-08-01T09:04:23.452486+00:00"
        },
        {
            "id": 2429,
            "numero": 13,
            "titulo": "Capítulo 13",
            "dataPublicacao": "2025-08-01T09:04:21.280135+00:00"
        },
        {
            "id": 2428,
            "numero": 12,
            "titulo": "Capítulo 12",
            "dataPublicacao": "2025-08-01T09:04:29.357996+00:00"
        },
        {
            "id": 2427,
            "numero": 11,
            "titulo": "Capítulo 11",
            "dataPublicacao": "2025-08-01T09:04:18.701008+00:00"
        },
        {
            "id": 2426,
            "numero": 10,
            "titulo": "Capítulo 10",
            "dataPublicacao": "2025-08-01T09:04:16.332200+00:00"
        },
        {
            "id": 2425,
            "numero": 9,
            "titulo": "Capítulo 9",
            "dataPublicacao": "2025-08-01T09:04:12.761165+00:00"
        },
        {
            "id": 2424,
            "numero": 8,
            "titulo": "Capítulo 8",
            "dataPublicacao": "2025-08-01T09:04:14.117576+00:00"
        },
        {
            "id": 2423,
            "numero": 7,
            "titulo": "Capítulo 7",
            "dataPublicacao": "2025-08-01T09:04:15.418849+00:00"
        },
        {
            "id": 2422,
            "numero": 6,
            "titulo": "Capítulo 6",
            "dataPublicacao": "2025-08-01T09:04:06.184169+00:00"
        },
        {
            "id": 2421,
            "numero": 5,
            "titulo": "Capítulo 5",
            "dataPublicacao": "2025-08-01T09:04:05.629593+00:00"
        },
        {
            "id": 2420,
            "numero": 4,
            "titulo": "Capítulo 4",
            "dataPublicacao": "2025-08-01T09:04:02.645038+00:00"
        },
        {
            "id": 2419,
            "numero": 3,
            "titulo": "Capítulo 3",
            "dataPublicacao": "2025-08-01T09:04:04.639767+00:00"
        },
        {
            "id": 2418,
            "numero": 2,
            "titulo": "Capítulo 2",
            "dataPublicacao": "2025-08-01T09:04:12.247584+00:00"
        },
        {
            "id": 2347,
            "numero": 1,
            "titulo": "Capítulo 1",
            "dataPublicacao": "2025-08-01T08:47:10.253936+00:00"
        },
        {
            "id": 77062,
            "numero": 0,
            "titulo": "Capítulo 0",
            "dataPublicacao": "2025-09-03T19:34:18.001036+00:00"
        }
    ]
}