{
    "id": "subindo-de-nivel-na-masmorra-exclusiva",
    "meta": {
        "titulo": "Subindo de Nível na Masmorra Exclusiva",
        "tituloAlternativo": "",
        "descricao": "O caçador Kang Jin-hyeok é da categoria D há anos. Seus dias eram preenchidos com empregos temporários, incapazes de progredir devido às áreas de caça controladas por grandes guildas.  Um dia, uma masmorra surge em seu quarto. \"Isso é... uma masmorra?\" Agora em posse da masmorra, Jinhyuk começa a caçar com sucesso, a subir de nível e a ficar mais forte a cada dia... \"Esperem para ver, seus canalhas das grandes guildas que me desprezaram! Vou me tornar mais forte com essa masmorra!\"",
        "ano": 2025,
        "status": "Em andamento",
        "autor": "",
        "artista": ""
    },
    "imagens": {
        "capa": "https://cdn.nexustoons.com/covers/b3bb9fd202b4daf9_1770390391794402357.webp",
        "banner": ""
    },
    "generos": [
        "Artes Marciais",
        "Aventura",
        "Ação",
        "Drama",
        "Fantasia"
    ]
}